neuralist
